[
    {
        "id": "510000198605217752",
        "username": "Margaret Hall",
        "phone": "17514765412",
        "email": "s.bpvuv@uqjefku.ee",
        "roles": "editor",
        "status": false,
        "createTime": "1990-05-17 23:43:36"
    },
    {
        "id": "540000199611068853",
        "username": "Anthony Williams",
        "phone": "14324574568",
        "email": "j.yzqo@ydwi.tc",
        "roles": "admin",
        "status": true,
        "createTime": "2005-10-08 13:06:12"
    },
    {
        "id": "21000019760115658X",
        "username": "Laura White",
        "phone": "14528534265",
        "email": "o.ufy@iyzxmsaq.td",
        "roles": "editor",
        "status": false,
        "createTime": "1986-01-15 14:40:43"
    },
    {
        "id": "99000019700113124X",
        "username": "Matthew Clark",
        "phone": "16611992073",
        "email": "s.fqewq@pnne.cz",
        "roles": "admin",
        "status": true,
        "createTime": "2006-11-18 08:07:07"
    },
    {
        "id": "530000200512300796",
        "username": "Steven Lewis",
        "phone": "16325335673",
        "email": "j.xjtoy@qxihuso.ag",
        "roles": "editor",
        "status": false,
        "createTime": "1989-02-28 20:34:50"
    },
    {
        "id": "310000197409047467",
        "username": "Daniel Lopez",
        "phone": "17635513485",
        "email": "u.dbct@yornvvbw.sj",
        "roles": "editor",
        "status": true,
        "createTime": "1970-03-09 13:19:47"
    },
    {
        "id": "440000198308255578",
        "username": "Jennifer Thomas",
        "phone": "13605865838",
        "email": "z.sgcayc@qtukb.ro",
        "roles": "admin",
        "status": false,
        "createTime": "1972-11-29 20:16:25"
    },
    {
        "id": "330000198805173121",
        "username": "Timothy Williams",
        "phone": "18844588270",
        "email": "u.tjfy@qjqb.ms",
        "roles": "editor",
        "status": true,
        "createTime": "2012-02-19 23:00:53"
    },
    {
        "id": "330000199807078464",
        "username": "David Gonzalez",
        "phone": "14537842575",
        "email": "i.abblys@qujtcujfy.cc",
        "roles": "admin",
        "status": true,
        "createTime": "2016-03-26 07:31:37"
    },
    {
        "id": "540000201102236687",
        "username": "Melissa Thompson",
        "phone": "16325867936",
        "email": "f.jhyo@yceqpg.aw",
        "roles": "admin",
        "status": true,
        "createTime": "2020-07-04 01:27:22"
    },
    {
        "id": "350000199501151167",
        "username": "Sandra Miller",
        "phone": "16083575382",
        "email": "i.fivsee@hxngmp.se",
        "roles": "admin",
        "status": true,
        "createTime": "1976-04-22 13:01:44"
    },
    {
        "id": "63000019750124613X",
        "username": "Anthony Jackson",
        "phone": "18686571289",
        "email": "p.zpfezf@egjwgixnxy.lt",
        "roles": "editor",
        "status": false,
        "createTime": "1995-10-15 04:23:46"
    },
    {
        "id": "210000201708118267",
        "username": "Anna Rodriguez",
        "phone": "18661751143",
        "email": "s.ewvcvy@mttdddr.ne",
        "roles": "admin",
        "status": true,
        "createTime": "1988-02-11 23:52:57"
    },
    {
        "id": "420000201705268154",
        "username": "Timothy Williams",
        "phone": "15109724217",
        "email": "y.kuw@hgcz.gov.cn",
        "roles": "editor",
        "status": true,
        "createTime": "1986-02-18 22:44:04"
    },
    {
        "id": "320000201308060153",
        "username": "Kimberly Young",
        "phone": "18288758269",
        "email": "a.hhnkehk@mwunv.nu",
        "roles": "admin",
        "status": true,
        "createTime": "1990-12-18 17:35:59"
    },
    {
        "id": "650000198806189437",
        "username": "Jennifer Williams",
        "phone": "17144735291",
        "email": "f.xemhfoaty@wfqarkwtvi.pm",
        "roles": "admin",
        "status": true,
        "createTime": "1989-10-29 02:02:50"
    },
    {
        "id": "530000201107222223",
        "username": "Robert Lewis",
        "phone": "14263178312",
        "email": "m.gwtjpwz@fykvndwlp.cv",
        "roles": "admin",
        "status": false,
        "createTime": "1989-01-11 10:37:01"
    },
    {
        "id": "64000020011223211X",
        "username": "Steven Wilson",
        "phone": "19372453785",
        "email": "o.oxqzijhx@uypcfkuv.ms",
        "roles": "admin",
        "status": true,
        "createTime": "1970-06-04 11:41:18"
    },
    {
        "id": "64000019951130105X",
        "username": "Sharon Garcia",
        "phone": "18266862374",
        "email": "p.htlcqy@mbujh.in",
        "roles": "editor",
        "status": false,
        "createTime": "1977-04-08 15:09:26"
    },
    {
        "id": "810000201605276889",
        "username": "Betty Thomas",
        "phone": "15562678551",
        "email": "t.qskdwrk@gkzdmygh.jo",
        "roles": "editor",
        "status": false,
        "createTime": "1996-08-07 15:36:06"
    },
    {
        "id": "430000197005045438",
        "username": "Sandra Martinez",
        "phone": "19326837518",
        "email": "t.dsghdsjmec@fqbrejnlbt.pf",
        "roles": "editor",
        "status": true,
        "createTime": "2005-11-19 01:58:56"
    },
    {
        "id": "370000201807018354",
        "username": "Barbara Hall",
        "phone": "19421182724",
        "email": "h.svipkxy@ghbjo.mc",
        "roles": "admin",
        "status": true,
        "createTime": "1972-02-06 19:48:18"
    },
    {
        "id": "150000197812142245",
        "username": "Richard Perez",
        "phone": "14506781027",
        "email": "s.dosbdkkt@zbtikk.sk",
        "roles": "editor",
        "status": true,
        "createTime": "1992-01-18 09:35:57"
    },
    {
        "id": "130000200703028479",
        "username": "Angela Brown",
        "phone": "15757873508",
        "email": "n.ugfybjjr@vmjltfgieh.be",
        "roles": "admin",
        "status": true,
        "createTime": "1979-08-25 19:49:36"
    },
    {
        "id": "15000019821018328X",
        "username": "Paul Clark",
        "phone": "18791111237",
        "email": "b.upjcfybub@iqsq.bg",
        "roles": "editor",
        "status": true,
        "createTime": "1973-11-20 14:45:02"
    },
    {
        "id": "410000198111075674",
        "username": "John Smith",
        "phone": "15867858527",
        "email": "k.sdxu@pwpzdsnp.ee",
        "roles": "admin",
        "status": false,
        "createTime": "1996-08-19 07:05:41"
    },
    {
        "id": "110000198308012561",
        "username": "Thomas Jones",
        "phone": "13485524437",
        "email": "t.nfjxujvw@lien.cc",
        "roles": "editor",
        "status": false,
        "createTime": "2006-02-07 21:16:21"
    },
    {
        "id": "450000200402115047",
        "username": "William Williams",
        "phone": "18462314472",
        "email": "k.ofbzf@bytqjhgwoj.cf",
        "roles": "editor",
        "status": true,
        "createTime": "2018-02-10 11:07:06"
    },
    {
        "id": "460000197111242430",
        "username": "Cynthia Allen",
        "phone": "15853678713",
        "email": "h.bvcgg@bkreolbhfj.gp",
        "roles": "admin",
        "status": false,
        "createTime": "2000-10-28 04:38:00"
    },
    {
        "id": "65000019741225588X",
        "username": "Laura Thomas",
        "phone": "17633244112",
        "email": "i.oixju@frpjjp.cm",
        "roles": "admin",
        "status": false,
        "createTime": "1992-06-12 19:08:09"
    },
    {
        "id": "110000197606103942",
        "username": "Barbara Hernandez",
        "phone": "16861845780",
        "email": "y.ysih@nqqzrd.tv",
        "roles": "admin",
        "status": false,
        "createTime": "1998-12-02 18:45:12"
    },
    {
        "id": "310000200106173946",
        "username": "Kimberly Moore",
        "phone": "16645441270",
        "email": "q.rskbdjby@txbol.et",
        "roles": "admin",
        "status": false,
        "createTime": "2021-11-21 19:59:45"
    },
    {
        "id": "640000201212034836",
        "username": "Donald Thomas",
        "phone": "14485378728",
        "email": "e.rgsotuzfd@gqhikdr.ve",
        "roles": "admin",
        "status": true,
        "createTime": "2004-08-13 20:59:27"
    },
    {
        "id": "120000199004242372",
        "username": "William Robinson",
        "phone": "16742472823",
        "email": "r.fmpngcn@fmhc.ml",
        "roles": "admin",
        "status": true,
        "createTime": "1998-04-25 07:34:31"
    },
    {
        "id": "360000201208077051",
        "username": "Cynthia Wilson",
        "phone": "14107778623",
        "email": "i.hmlvy@tjvxzvf.fk",
        "roles": "admin",
        "status": true,
        "createTime": "2002-01-23 13:28:52"
    },
    {
        "id": "50000020060101450X",
        "username": "Maria White",
        "phone": "15544631621",
        "email": "f.rnx@uutb.lv",
        "roles": "editor",
        "status": true,
        "createTime": "1992-07-21 18:25:44"
    },
    {
        "id": "430000199507168824",
        "username": "George Johnson",
        "phone": "15136813177",
        "email": "x.kvdssyctm@vsontxdjl.ph",
        "roles": "admin",
        "status": false,
        "createTime": "1988-08-21 14:55:02"
    },
    {
        "id": "340000197207114428",
        "username": "Richard Thompson",
        "phone": "15354997563",
        "email": "m.pfzgq@cnhgf.vn",
        "roles": "editor",
        "status": true,
        "createTime": "2013-12-01 11:18:10"
    },
    {
        "id": "35000019840415488X",
        "username": "Helen Hernandez",
        "phone": "14241381304",
        "email": "u.ldrpvhnbm@xaiihgruw.pf",
        "roles": "admin",
        "status": false,
        "createTime": "2007-07-22 17:03:29"
    },
    {
        "id": "510000197309291515",
        "username": "Gary Martin",
        "phone": "16527026097",
        "email": "p.grwtdp@jqhyzpxv.lr",
        "roles": "editor",
        "status": false,
        "createTime": "1987-04-30 03:47:51"
    },
    {
        "id": "210000197410104293",
        "username": "Susan Robinson",
        "phone": "14115546238",
        "email": "x.mnpyji@pirr.gf",
        "roles": "admin",
        "status": true,
        "createTime": "1975-10-27 02:44:42"
    },
    {
        "id": "330000201705286799",
        "username": "Paul Robinson",
        "phone": "16725978497",
        "email": "u.zzpqm@cbd.iq",
        "roles": "editor",
        "status": false,
        "createTime": "2001-03-26 05:47:59"
    },
    {
        "id": "430000201107077819",
        "username": "Ruth Johnson",
        "phone": "15485414339",
        "email": "r.dnuzmgrp@wisrtg.gp",
        "roles": "admin",
        "status": false,
        "createTime": "2020-03-07 03:22:23"
    },
    {
        "id": "630000201803056365",
        "username": "Kevin Garcia",
        "phone": "19934449413",
        "email": "x.llja@ldruwplfi.nr",
        "roles": "editor",
        "status": true,
        "createTime": "1984-04-12 10:02:17"
    },
    {
        "id": "120000198503107568",
        "username": "Melissa Lopez",
        "phone": "17054935307",
        "email": "c.umy@nbvho.jm",
        "roles": "admin",
        "status": true,
        "createTime": "2018-09-05 17:40:29"
    },
    {
        "id": "430000202304160253",
        "username": "Jeffrey Taylor",
        "phone": "13134874213",
        "email": "l.krsnsllbx@remix.mo",
        "roles": "editor",
        "status": false,
        "createTime": "1993-05-15 02:19:57"
    },
    {
        "id": "630000202108176095",
        "username": "Jeffrey Lewis",
        "phone": "15131220481",
        "email": "w.tmceqxhtun@jirugj.kn",
        "roles": "admin",
        "status": true,
        "createTime": "2007-11-04 04:40:40"
    },
    {
        "id": "51000019860814662X",
        "username": "Sarah Harris",
        "phone": "17478874288",
        "email": "o.omocxphnhm@oijfugo.sk",
        "roles": "editor",
        "status": false,
        "createTime": "2015-08-03 09:01:52"
    },
    {
        "id": "410000201003032815",
        "username": "Laura Smith",
        "phone": "15634173563",
        "email": "s.aptvgdz@ggboogz.sl",
        "roles": "editor",
        "status": true,
        "createTime": "1986-01-16 19:21:26"
    },
    {
        "id": "140000199304085480",
        "username": "Betty Martinez",
        "phone": "18015224327",
        "email": "m.cdcbfzeh@mpkyqfpx.bg",
        "roles": "admin",
        "status": false,
        "createTime": "1986-12-01 20:01:01"
    },
    {
        "id": "120000199701160444",
        "username": "Cynthia Harris",
        "phone": "16227585323",
        "email": "p.ngjrkzr@mvfnukdjlb.ie",
        "roles": "editor",
        "status": false,
        "createTime": "2015-01-18 15:01:00"
    },
    {
        "id": "610000200608307132",
        "username": "Susan Moore",
        "phone": "18688228631",
        "email": "c.ehvxo@uoknabxdp.bv",
        "roles": "admin",
        "status": true,
        "createTime": "2008-07-07 13:16:44"
    },
    {
        "id": "520000199704249529",
        "username": "Susan Miller",
        "phone": "17467231571",
        "email": "g.yxejulg@numbcvhf.my",
        "roles": "admin",
        "status": true,
        "createTime": "1983-09-21 00:47:23"
    },
    {
        "id": "420000197701132824",
        "username": "Deborah Robinson",
        "phone": "17169416764",
        "email": "m.xkyi@wlinjmo.coop",
        "roles": "admin",
        "status": false,
        "createTime": "1981-01-16 12:30:52"
    },
    {
        "id": "540000197605063520",
        "username": "Matthew Gonzalez",
        "phone": "14538896862",
        "email": "s.uitykbc@gpcfukvhm.bg",
        "roles": "editor",
        "status": true,
        "createTime": "2019-02-22 11:56:21"
    },
    {
        "id": "340000200412033322",
        "username": "Margaret Wilson",
        "phone": "15214735148",
        "email": "r.zwvspof@jorjqxy.lb",
        "roles": "admin",
        "status": false,
        "createTime": "1995-04-19 21:58:16"
    },
    {
        "id": "610000197810039544",
        "username": "Anthony Hernandez",
        "phone": "14379565809",
        "email": "x.shf@itjqklqksq.ck",
        "roles": "admin",
        "status": true,
        "createTime": "1978-12-13 12:12:58"
    },
    {
        "id": "520000201911204315",
        "username": "Carol Johnson",
        "phone": "15310831849",
        "email": "f.fxqpo@fwgscbnet.mg",
        "roles": "editor",
        "status": true,
        "createTime": "1999-02-21 04:06:15"
    },
    {
        "id": "140000201906158018",
        "username": "Joseph Lee",
        "phone": "16122677245",
        "email": "q.xnnuowhu@uyqwsp.ev",
        "roles": "admin",
        "status": false,
        "createTime": "1980-11-07 13:42:11"
    },
    {
        "id": "320000199811161656",
        "username": "Michael Perez",
        "phone": "19252683205",
        "email": "f.pdgvz@eqfzyqssq.zr",
        "roles": "admin",
        "status": false,
        "createTime": "1995-10-07 02:03:43"
    },
    {
        "id": "540000199911055261",
        "username": "Barbara Martinez",
        "phone": "15461805482",
        "email": "f.eklyr@mcjq.bw",
        "roles": "admin",
        "status": true,
        "createTime": "1998-07-02 10:04:02"
    },
    {
        "id": "810000201906053320",
        "username": "Steven Jackson",
        "phone": "13834557280",
        "email": "k.xyhxg@tqpn.lc",
        "roles": "admin",
        "status": false,
        "createTime": "2023-01-30 14:53:57"
    },
    {
        "id": "340000198708065315",
        "username": "Elizabeth Garcia",
        "phone": "16781358063",
        "email": "m.onzoqmox@dcam.to",
        "roles": "admin",
        "status": false,
        "createTime": "2008-07-18 10:18:30"
    },
    {
        "id": "610000200406051175",
        "username": "Joseph Clark",
        "phone": "15246585170",
        "email": "r.ndxwnfknc@bbeptwxtk.cy",
        "roles": "editor",
        "status": false,
        "createTime": "2019-06-11 21:55:32"
    },
    {
        "id": "140000201104212406",
        "username": "Elizabeth Walker",
        "phone": "16320126943",
        "email": "f.nzrrns@ebnuptfwj.tv",
        "roles": "editor",
        "status": true,
        "createTime": "1971-03-21 11:46:12"
    },
    {
        "id": "810000201301292572",
        "username": "Jeffrey Hernandez",
        "phone": "16416304211",
        "email": "v.epzfv@fhyiker.nr",
        "roles": "admin",
        "status": false,
        "createTime": "2000-05-30 14:10:15"
    },
    {
        "id": "500000199205135099",
        "username": "Michelle Johnson",
        "phone": "13517741044",
        "email": "e.aensvjkis@spbephnxrp.cd",
        "roles": "editor",
        "status": false,
        "createTime": "1983-11-20 23:41:03"
    },
    {
        "id": "220000201609248623",
        "username": "David Hernandez",
        "phone": "14233782632",
        "email": "r.hqxrqfclc@ywb.jo",
        "roles": "editor",
        "status": true,
        "createTime": "1974-03-27 05:12:48"
    },
    {
        "id": "500000197011119083",
        "username": "Jessica Jackson",
        "phone": "13716579948",
        "email": "i.hkqkov@xmy.us",
        "roles": "editor",
        "status": true,
        "createTime": "1974-04-21 14:12:30"
    },
    {
        "id": "440000197908261627",
        "username": "Laura Hernandez",
        "phone": "15823023051",
        "email": "i.xwwwqnr@eogseq.bn",
        "roles": "admin",
        "status": true,
        "createTime": "1992-02-03 06:12:31"
    },
    {
        "id": "430000197108182427",
        "username": "Jose Walker",
        "phone": "18246642826",
        "email": "p.genrv@gsebh.bn",
        "roles": "editor",
        "status": true,
        "createTime": "2019-02-19 01:08:55"
    },
    {
        "id": "530000198612177086",
        "username": "Richard Perez",
        "phone": "19388678644",
        "email": "d.iykwzused@girji.mm",
        "roles": "editor",
        "status": false,
        "createTime": "1976-08-13 05:50:59"
    },
    {
        "id": "360000198702268932",
        "username": "Melissa Clark",
        "phone": "17562103517",
        "email": "j.jwjontrtt@hac.mr",
        "roles": "editor",
        "status": false,
        "createTime": "2009-09-16 19:02:05"
    },
    {
        "id": "650000201806073500",
        "username": "Mary Harris",
        "phone": "15285717721",
        "email": "e.eyixy@enh.hk",
        "roles": "editor",
        "status": true,
        "createTime": "2002-06-02 15:24:13"
    },
    {
        "id": "650000201712035909",
        "username": "Eric Gonzalez",
        "phone": "15877128183",
        "email": "y.ktydd@iejbfqdejx.bm",
        "roles": "editor",
        "status": true,
        "createTime": "2023-09-28 11:09:16"
    },
    {
        "id": "650000199904243972",
        "username": "Angela Young",
        "phone": "17345211988",
        "email": "j.mvg@ksopmw.sc",
        "roles": "editor",
        "status": true,
        "createTime": "2005-04-11 08:10:36"
    },
    {
        "id": "120000197608234868",
        "username": "Dorothy Clark",
        "phone": "18059848139",
        "email": "b.ygnpbn@cxrfo.hk",
        "roles": "editor",
        "status": false,
        "createTime": "2015-11-21 18:44:58"
    },
    {
        "id": "360000199204138881",
        "username": "Eric Hernandez",
        "phone": "16810556737",
        "email": "d.pdef@bassfxgw.cl",
        "roles": "editor",
        "status": true,
        "createTime": "1986-08-22 15:13:12"
    },
    {
        "id": "440000197612313555",
        "username": "Susan Anderson",
        "phone": "14876843452",
        "email": "k.gdkfkh@plvrwro.net",
        "roles": "admin",
        "status": false,
        "createTime": "1993-06-19 09:25:28"
    },
    {
        "id": "820000201805286389",
        "username": "Elizabeth Young",
        "phone": "14380532760",
        "email": "g.yqdfqqnpu@iap.eh",
        "roles": "admin",
        "status": false,
        "createTime": "1999-05-15 23:00:27"
    },
    {
        "id": "610000202109261431",
        "username": "Mary Perez",
        "phone": "16519172446",
        "email": "o.vdytm@jdtublmeh.it",
        "roles": "editor",
        "status": true,
        "createTime": "1999-06-22 22:16:38"
    },
    {
        "id": "530000200612277474",
        "username": "James Robinson",
        "phone": "19337455135",
        "email": "f.yjqlwnnjk@bxzqfzqb.gp",
        "roles": "admin",
        "status": false,
        "createTime": "1991-06-18 17:00:01"
    },
    {
        "id": "440000202010241180",
        "username": "Amy Lewis",
        "phone": "16163223618",
        "email": "t.lrddq@ybhm.kw",
        "roles": "editor",
        "status": true,
        "createTime": "1997-12-10 05:44:51"
    },
    {
        "id": "120000198606303553",
        "username": "Donald Lewis",
        "phone": "13817631737",
        "email": "x.pvjutcocbo@hhkqfb.ck",
        "roles": "admin",
        "status": false,
        "createTime": "2023-06-06 22:26:48"
    },
    {
        "id": "620000197610064536",
        "username": "Helen Young",
        "phone": "19587245229",
        "email": "t.qjddbiakgm@oceul.nz",
        "roles": "admin",
        "status": false,
        "createTime": "1983-06-20 05:49:23"
    },
    {
        "id": "610000202202154315",
        "username": "Edward Hall",
        "phone": "17891653896",
        "email": "p.oyruw@lmturul.pm",
        "roles": "editor",
        "status": true,
        "createTime": "1988-02-28 22:44:20"
    },
    {
        "id": "14000019780712135X",
        "username": "Ronald Thompson",
        "phone": "17168346225",
        "email": "k.ejrh@puhblete.sj",
        "roles": "admin",
        "status": false,
        "createTime": "1996-06-22 18:16:19"
    },
    {
        "id": "82000020210316877X",
        "username": "Ruth Wilson",
        "phone": "18375746933",
        "email": "m.qvnovdr@qbodqoxmp.nl",
        "roles": "editor",
        "status": true,
        "createTime": "1996-11-10 17:44:20"
    },
    {
        "id": "130000197002054717",
        "username": "Brian Thomas",
        "phone": "14574439541",
        "email": "r.onb@xvlqvgu.ci",
        "roles": "admin",
        "status": true,
        "createTime": "1993-07-02 07:25:59"
    },
    {
        "id": "64000019960719587X",
        "username": "Patricia Williams",
        "phone": "16912668438",
        "email": "b.qedvnliurq@xlnfy.kz",
        "roles": "editor",
        "status": false,
        "createTime": "2015-05-15 06:27:44"
    },
    {
        "id": "430000198302218109",
        "username": "Jennifer Brown",
        "phone": "17002163848",
        "email": "s.rsdhspjai@ebvvpionj.hk",
        "roles": "editor",
        "status": false,
        "createTime": "2017-05-02 17:47:45"
    },
    {
        "id": "32000019710312146X",
        "username": "Amy Martin",
        "phone": "17733306649",
        "email": "k.cseypn@zjqdi.wf",
        "roles": "admin",
        "status": true,
        "createTime": "1984-10-16 02:36:04"
    },
    {
        "id": "710000197303056757",
        "username": "Barbara Taylor",
        "phone": "15288175072",
        "email": "c.hvgvfwo@mkezfeg.sz",
        "roles": "admin",
        "status": false,
        "createTime": "1987-09-12 00:58:16"
    },
    {
        "id": "310000199603067444",
        "username": "John Johnson",
        "phone": "16585118216",
        "email": "g.tljfcv@ytdz.uy",
        "roles": "admin",
        "status": true,
        "createTime": "1983-09-05 14:14:02"
    },
    {
        "id": "510000199402054257",
        "username": "Sandra Lewis",
        "phone": "13077561283",
        "email": "q.lvetxosoi@lbyr.ms",
        "roles": "admin",
        "status": true,
        "createTime": "2017-06-28 00:13:51"
    },
    {
        "id": "520000201708173744",
        "username": "Deborah Miller",
        "phone": "16550646768",
        "email": "l.ilm@ukgcrbl.lt",
        "roles": "admin",
        "status": false,
        "createTime": "1991-07-11 15:22:46"
    },
    {
        "id": "530000201608163479",
        "username": "Patricia Young",
        "phone": "19840384481",
        "email": "c.mecoagxv@goleqsbsp.yu",
        "roles": "editor",
        "status": false,
        "createTime": "2008-05-25 23:29:55"
    },
    {
        "id": "820000198410272156",
        "username": "Jason Hall",
        "phone": "15126026906",
        "email": "t.odymwnch@abvhyqa.gu",
        "roles": "admin",
        "status": true,
        "createTime": "1998-11-28 10:30:55"
    },
    {
        "id": "450000199707102014",
        "username": "Angela Gonzalez",
        "phone": "18896576813",
        "email": "h.ysk@svgxf.pw",
        "roles": "editor",
        "status": false,
        "createTime": "2012-01-15 22:01:50"
    },
    {
        "id": "210000200608205350",
        "username": "Barbara Perez",
        "phone": "17179868705",
        "email": "x.irgjk@bqqltgan.tc",
        "roles": "editor",
        "status": true,
        "createTime": "1995-02-28 01:47:36"
    }
]
